LICENSE
bodhiext/sentence_transformers/__init__.py
bodhiext/sentence_transformers/_sentence_transformer_embedder.py
bodhiext/sentence_transformers/_version.py
bodhiext_sentence_transformers-0.1.2.dist-info/LICENSE
bodhiext_sentence_transformers-0.1.2.dist-info/METADATA
bodhiext_sentence_transformers-0.1.2.dist-info/WHEEL
bodhiext_sentence_transformers-0.1.2.dist-info/entry_points.txt
bodhiext_sentence_transformers-0.1.2.dist-info/RECORD
